nasapy/__init__.py
nasapy/api.py
nasapy-0.2.7.dist-info/LICENSE.txt
nasapy-0.2.7.dist-info/METADATA
nasapy-0.2.7.dist-info/WHEEL
nasapy-0.2.7.dist-info/top_level.txt
nasapy-0.2.7.dist-info/RECORD
